GitxClone/__init__.py
GitxClone/core.py
GitxClone-1.0.1.dist-info/LICENSE
GitxClone-1.0.1.dist-info/METADATA
GitxClone-1.0.1.dist-info/WHEEL
GitxClone-1.0.1.dist-info/top_level.txt
GitxClone-1.0.1.dist-info/RECORD
